stompypy/__init__.py
stompypy/client.py
stompypy/constants.py
stompypy/exceptions.py
stompypy/frame.py
stompypy/listeners.py
stompypy/logging_config.py
stompypy/managers.py
stompypy/sender.py
stompypy/stomp.py
stompypy/test.py
stompypy-0.4.0.dist-info/LICENSE
stompypy-0.4.0.dist-info/METADATA
stompypy-0.4.0.dist-info/WHEEL
stompypy-0.4.0.dist-info/RECORD
