Metadata-Version: 2.1
Name: stompypy
Version: 0.4.0
Summary: The StompyPy is a simple implementation of the STOMP (Simple Text Oriented Messaging Protocol) protocol. It provides an easy way to connect to and exchange STOMP frames with a STOMP server.
Home-page: https://github.com/hugobrilhante/stompypy
License: MIT
Author: Hugo Brilhante
Author-email: hugobrilhante@gmail.com
Requires-Python: >=3.12,<4.0
Classifier: License :: OSI Approved :: MIT License
Classifier: Programming Language :: Python :: 3
Classifier: Programming Language :: Python :: 3.12
Project-URL: Repository, https://github.com/hugobrilhante/stompypy
